{"fumbles": 1.0, "fumblesLost": 0.0, "fumblesForced": 0.0, "fumblesRecovered": 0.0, "fumblesRecoveredYards": 0.0, "fumblesTouchdowns": 0.0, "gamesPlayed": 17.0, "offensiveTwoPtReturns": 0.0, "offensiveFumblesTouchdowns": 0.0, "defensiveFumblesTouchdowns": 0.0, "avgGain": 0.0, "completionPct": 0.0, "completions": 0.0, "ESPNQBRating": 0.0, "interceptionPct": 0.0, "interceptions": 0.0, "longPassing": 0.0, "netPassingYards": -2.0, "netPassingYardsPerGame": -0.11764705926179886, "netTotalYards": -2.0, "netYardsPerGame": -0.11764705926179886, "passingAttempts": 0.0, "passingBigPlays": 0.0, "passingFirstDowns": 0.0, "passingFumbles": 0.0, "passingFumblesLost": 0.0, "passingTouchdownPct": 0.0, "passingTouchdowns": 0.0, "passingYards": 0.0, "passingYardsAfterCatch": 0.0, "passingYardsAtCatch": 0.0, "passingYardsPerGame": 0.0, "QBRating": 0.0, "sacks": 0.0, "sackYardsLost": 2.0, "teamGamesPlayed": 17.0, "totalOffensivePlays": 1.0, "totalPointsPerGame": 3.5290000438690186, "totalTouchdowns": 10.0, "totalYards": 1225.0, "totalYardsFromScrimmage": 1225.0, "twoPointPassConvs": 0.0, "twoPtPass": 0.0, "twoPtPassAttempts": 0.0, "yardsFromScrimmagePerGame": 72.05882263183594, "yardsPerCompletion": 0.0, "yardsPerGame": 72.05882263183594, "yardsPerPassAttempt": 0.0, "netYardsPerPassAttempt": -2.0, "QBR": 0.74, "adjQBR": 0.43, "quarterbackRating": 0.0, "ESPNRBRating": 0.0, "longRushing": 0.0, "rushingAttempts": 0.0, "rushingBigPlays": 0.0, "rushingFirstDowns": 0.0, "rushingFumbles": 0.0, "rushingFumblesLost": 0.0, "rushingTouchdowns": 0.0, "rushingYards": 0.0, "rushingYardsPerGame": 0.0, "stuffs": 0.0, "stuffYardsLost": 0.0, "twoPointRushConvs": 0.0, "twoPtRush": 0.0, "twoPtRushAttempts": 0.0, "yardsPerRushAttempt": 0.0, "ESPNWRRating": 2090.0, "longReception": 61.0, "receivingBigPlays": 12.0, "receivingFirstDowns": 66.0, "receivingFumbles": 1.0, "receivingFumblesLost": 0.0, "receivingTargets": 164.0, "receivingTouchdowns": 10.0, "receivingYards": 1225.0, "receivingYardsAfterCatch": 326.0, "receivingYardsAtCatch": 899.0, "receivingYardsPerGame": 72.05882263183594, "receptions": 103.0, "twoPointRecConvs": 0.0, "twoPtReception": 0.0, "twoPtReceptionAttempts": 0.0, "yardsPerReception": 11.892999649047852, "assistTackles": 0.0, "avgInterceptionYards": 0.0, "avgSackYards": 0.0, "avgStuffYards": 0.0, "blockedFieldGoalTouchdowns": 0.0, "blockedPuntTouchdowns": 0.0, "hurries": 0.0, "kicksBlocked": 0.0, "longInterception": 0.0, "miscTouchdowns": 0.0, "passesBattedDown": 0.0, "passesDefended": 0.0, "QBHits": 0.0, "twoPtReturns": 0.0, "sackYards": 0.0, "safeties": 0.0, "soloTackles": 3.0, "stuffYards": 0.0, "tacklesForLoss": 0.0, "tacklesYardsLost": 0.0, "totalTackles": 3.0, "yardsAllowed": 0.0, "pointsAllowed": 0.0, "onePtSafetiesMade": 0.0, "interceptionTouchdowns": 0.0, "interceptionYards": 0.0, "defensivePoints": 0.0, "fieldGoals": 0.0, "kickExtraPoints": 0.0, "miscPoints": 0.0, "returnTouchdowns": 0.0, "totalPoints": 60.0, "totalTwoPointConvs": 0.0} 